LICENSE
MANIFEST.in
README.md
setup.py
bddl/__init__.py
bddl/activity.py
bddl/activity_manifest.txt
bddl/activity_to_preselected_scenes.json
bddl/backend_abc.py
bddl/condition_evaluation.py
bddl/config.py
bddl/hierarchy_all.json
bddl/hierarchy_articles.json
bddl/hierarchy_owned.json
bddl/logic_base.py
bddl/object_taxonomy.py
bddl/parsing.py
bddl/utils.py
bddl/__pycache__/__init__.cpython-38.pyc
bddl/__pycache__/activity.cpython-38.pyc
bddl/__pycache__/backend_abc.cpython-38.pyc
bddl/__pycache__/condition_evaluation.cpython-38.pyc
bddl/__pycache__/config.cpython-38.pyc
bddl/__pycache__/logic_base.cpython-38.pyc
bddl/__pycache__/object_taxonomy.cpython-38.pyc
bddl/__pycache__/parsing.cpython-38.pyc
bddl/__pycache__/utils.cpython-38.pyc
bddl/activity_definitions/domain_igibson.bddl
bddl/activity_definitions/assembling_gift_baskets/problem0.bddl
bddl/activity_definitions/bottling_fruit/problem0.bddl
bddl/activity_definitions/boxing_books_up_for_storage/problem0.bddl
bddl/activity_definitions/bringing_in_wood/problem0.bddl
bddl/activity_definitions/brushing_lint_off_clothing/problem0.bddl
bddl/activity_definitions/chopping_vegetables/problem0.bddl
bddl/activity_definitions/cleaning_a_car/problem0.bddl
bddl/activity_definitions/cleaning_barbecue_grill/problem0.bddl
bddl/activity_definitions/cleaning_bathrooms/problem0.bddl
bddl/activity_definitions/cleaning_bathtub/problem0.bddl
bddl/activity_definitions/cleaning_bedroom/problem0.bddl
bddl/activity_definitions/cleaning_carpets/problem0.bddl
bddl/activity_definitions/cleaning_closet/problem0.bddl
bddl/activity_definitions/cleaning_cupboards/problem0.bddl
bddl/activity_definitions/cleaning_floors/problem0.bddl
bddl/activity_definitions/cleaning_freezer/problem0.bddl
bddl/activity_definitions/cleaning_garage/problem0.bddl
bddl/activity_definitions/cleaning_high_chair/problem0.bddl
bddl/activity_definitions/cleaning_kitchen_cupboard/problem0.bddl
bddl/activity_definitions/cleaning_microwave_oven/problem0.bddl
bddl_eval.egg-info/PKG-INFO
bddl_eval.egg-info/SOURCES.txt
bddl_eval.egg-info/dependency_links.txt
bddl_eval.egg-info/not-zip-safe
bddl_eval.egg-info/requires.txt
bddl_eval.egg-info/top_level.txt
