Metadata-Version: 2.1
Name: bddl-eval
Version: 1.0.1
Home-page: https://github.com/StanfordVL/bddl
Author: Stanford University
License-File: LICENSE
Requires-Dist: pytest
Requires-Dist: numpy
Requires-Dist: networkx
Requires-Dist: jupytext
